{
  "schema_version": 2,
  "commit": "73b4bd5",
  "renderer": "gl",
  "machine": {
    "cpu": "AMD Ryzen Threadripper 3970X 32-Core Processor",
    "cores": 64,
    "ram_gb": 191.9,
    "os": "10.0.22631"
  },
  "total_frames": 566,
  "markers": {
    "Frame": {
      "min": 2.781,
      "max": 195.915,
      "avg": 16.7917,
      "p50": 16.5396,
      "p99": 18.0626,
      "p99_9": 95.6114
    },
    "Frame/Input": {
      "min": 0.0038,
      "max": 0.4779,
      "avg": 0.0085,
      "p50": 0.0064,
      "p99": 0.0538,
      "p99_9": 0.293
    },
    "Frame/Render": {
      "min": 0.828,
      "max": 1.8353,
      "avg": 1.0495,
      "p50": 0.9539,
      "p99": 1.6781,
      "p99_9": 1.7872
    },
    "Frame/Render_gpu": {
      "min": 0.2376,
      "max": 6.3928,
      "avg": 1.4372,
      "p50": 1.663,
      "p99": 6.0775,
      "p99_9": 6.3899
    },
    "Frame/Render/Skybox": {
      "min": 0.0189,
      "max": 0.1284,
      "avg": 0.0474,
      "p50": 0.0455,
      "p99": 0.1025,
      "p99_9": 0.1202
    },
    "Frame/Render/Skybox_gpu": {
      "min": 0.0082,
      "max": 0.1638,
      "avg": 0.1014,
      "p50": 0.1311,
      "p99": 0.1618,
      "p99_9": 0.1638
    },
    "Frame/Render/Reflection": {
      "min": 0.3722,
      "max": 0.8721,
      "avg": 0.4742,
      "p50": 0.432,
      "p99": 0.7832,
      "p99_9": 0.8392
    },
    "Frame/Render/Reflection_gpu": {
      "min": 0.1157,
      "max": 5.548,
      "avg": 0.7761,
      "p50": 0.8581,
      "p99": 5.2846,
      "p99_9": 5.5451
    },
    "Frame/Render/Reflection/Skybox": {
      "min": 0.0287,
      "max": 0.1883,
      "avg": 0.0559,
      "p50": 0.0525,
      "p99": 0.1259,
      "p99_9": 0.1728
    },
    "Frame/Render/Reflection/Skybox_gpu": {
      "min": 0.0266,
      "max": 0.428,
      "avg": 0.2878,
      "p50": 0.3881,
      "p99": 0.4202,
      "p99_9": 0.4257
    },
    "Frame/Render/Reflection/Balls": {
      "min": 0.3403,
      "max": 0.7257,
      "avg": 0.4165,
      "p50": 0.3711,
      "p99": 0.6843,
      "p99_9": 0.7237
    },
    "Frame/Render/Reflection/Balls_gpu": {
      "min": 0.0727,
      "max": 5.0493,
      "avg": 0.4018,
      "p50": 0.365,
      "p99": 3.8961,
      "p99_9": 5.0476
    },
    "Frame/Render/Balls": {
      "min": 0.3465,
      "max": 0.7923,
      "avg": 0.4198,
      "p50": 0.3626,
      "p99": 0.7089,
      "p99_9": 0.7659
    },
    "Frame/Render/Balls_gpu": {
      "min": 0.0963,
      "max": 4.7043,
      "avg": 0.4012,
      "p50": 0.4403,
      "p99": 1.595,
      "p99_9": 3.6079
    },
    "Frame/Render/Terrain": {
      "min": 0.0048,
      "max": 0.0515,
      "avg": 0.0081,
      "p50": 0.0069,
      "p99": 0.0262,
      "p99_9": 0.0488
    },
    "Frame/Render/Terrain_gpu": {
      "min": 0.0041,
      "max": 0.1925,
      "avg": 0.115,
      "p50": 0.1526,
      "p99": 0.1833,
      "p99_9": 0.1919
    },
    "Frame/Render/Shadows": {
      "min": 0.0479,
      "max": 0.1678,
      "avg": 0.0752,
      "p50": 0.0744,
      "p99": 0.1328,
      "p99_9": 0.1574
    },
    "Frame/Render/Shadows_gpu": {
      "min": 0.0,
      "max": 1.2411,
      "avg": 0.006,
      "p50": 0.0031,
      "p99": 0.0762,
      "p99_9": 0.5856
    },
    "Frame/Render/Water": {
      "min": 0.014,
      "max": 0.0912,
      "avg": 0.0231,
      "p50": 0.0219,
      "p99": 0.052,
      "p99_9": 0.0772
    },
    "Frame/Render/Water_gpu": {
      "min": 0.0,
      "max": 2.3327,
      "avg": 0.0135,
      "p50": 0.0031,
      "p99": 0.0379,
      "p99_9": 2.3275
    },
    "Frame/Physics": {
      "min": 0.153,
      "max": 0.3544,
      "avg": 0.2453,
      "p50": 0.2445,
      "p99": 0.3416,
      "p99_9": 0.3504
    },
    "Frame/Physics/ApplyForces": {
      "min": 0.0257,
      "max": 0.062,
      "avg": 0.0311,
      "p50": 0.0301,
      "p99": 0.0601,
      "p99_9": 0.0618
    },
    "Frame/Physics/Broadphase": {
      "min": 0.0485,
      "max": 0.2025,
      "avg": 0.1242,
      "p50": 0.1254,
      "p99": 0.1814,
      "p99_9": 0.2005
    },
    "Frame/Physics/Narrowphase": {
      "min": 0.0002,
      "max": 0.0561,
      "avg": 0.0063,
      "p50": 0.0059,
      "p99": 0.0112,
      "p99_9": 0.032
    },
    "Frame/Physics/Terrain": {
      "min": 0.0003,
      "max": 0.1001,
      "avg": 0.0325,
      "p50": 0.0314,
      "p99": 0.0642,
      "p99_9": 0.0822
    },
    "Frame/Physics/Integrate": {
      "min": 0.0003,
      "max": 0.11,
      "avg": 0.0496,
      "p50": 0.0488,
      "p99": 0.0673,
      "p99_9": 0.1059
    },
    "Frame/Text": {
      "min": 0.8784,
      "max": 1.8735,
      "avg": 1.1066,
      "p50": 1.0753,
      "p99": 1.5685,
      "p99_9": 1.7763
    },
    "Frame/Text_gpu": {
      "min": 0.1372,
      "max": 2.4904,
      "avg": 0.2805,
      "p50": 0.2243,
      "p99": 1.8108,
      "p99_9": 2.4262
    },
    "Frame/PipelineSync": {
      "min": 0.0243,
      "max": 193.229,
      "avg": 14.3548,
      "p50": 14.2143,
      "p99": 15.1298,
      "p99_9": 93.0022
    },
    "Frame/VsyncWait": {
      "min": 0.012,
      "max": 0.1563,
      "avg": 0.0261,
      "p50": 0.0249,
      "p99": 0.0531,
      "p99_9": 0.1432
    }
  },
  "mem_start_mb": 60.28,
  "mem_restart_mb": 64.38,
  "mem_end_mb": 64.38
}