{
  "schema_version": 2,
  "commit": "731433e",
  "renderer": "dx12",
  "machine": {
    "cpu": "AMD Ryzen Threadripper 3970X 32-Core Processor",
    "cores": 64,
    "ram_gb": 191.9,
    "os": "10.0.22631"
  },
  "total_frames": 575,
  "markers": {
    "Frame": {
      "min": 3.189,
      "max": 24.2138,
      "avg": 16.5446,
      "p50": 16.5541,
      "p99": 23.6178,
      "p99_9": 24.1776
    },
    "Frame/Input": {
      "min": 0.0046,
      "max": 0.092,
      "avg": 0.0074,
      "p50": 0.0067,
      "p99": 0.0155,
      "p99_9": 0.0577
    },
    "Frame/Render": {
      "min": 1.9322,
      "max": 2.5329,
      "avg": 2.2028,
      "p50": 2.2014,
      "p99": 2.4611,
      "p99_9": 2.5271
    },
    "Frame/Render/Skybox": {
      "min": 0.0695,
      "max": 0.1632,
      "avg": 0.0984,
      "p50": 0.0977,
      "p99": 0.126,
      "p99_9": 0.1464
    },
    "Frame/Render/Reflection": {
      "min": 0.8653,
      "max": 1.1187,
      "avg": 0.9376,
      "p50": 0.929,
      "p99": 1.0703,
      "p99_9": 1.1038
    },
    "Frame/Render/Reflection/Skybox": {
      "min": 0.0321,
      "max": 0.0945,
      "avg": 0.0372,
      "p50": 0.0366,
      "p99": 0.0467,
      "p99_9": 0.08
    },
    "Frame/Render/Reflection/Balls": {
      "min": 0.8125,
      "max": 1.0441,
      "avg": 0.8813,
      "p50": 0.8717,
      "p99": 1.0146,
      "p99_9": 1.0347
    },
    "Frame/Render/Balls": {
      "min": 0.8091,
      "max": 0.9584,
      "avg": 0.8568,
      "p50": 0.8552,
      "p99": 0.9391,
      "p99_9": 0.9569
    },
    "Frame/Render/Terrain": {
      "min": 0.0089,
      "max": 0.0806,
      "avg": 0.0124,
      "p50": 0.0121,
      "p99": 0.0259,
      "p99_9": 0.0526
    },
    "Frame/Render/Shadows": {
      "min": 0.0395,
      "max": 0.1281,
      "avg": 0.058,
      "p50": 0.0575,
      "p99": 0.0767,
      "p99_9": 0.1004
    },
    "Frame/Render/Water": {
      "min": 0.0144,
      "max": 0.0284,
      "avg": 0.0199,
      "p50": 0.0198,
      "p99": 0.0261,
      "p99_9": 0.0281
    },
    "Frame/Physics": {
      "min": 0.1366,
      "max": 0.3366,
      "avg": 0.2347,
      "p50": 0.2349,
      "p99": 0.2875,
      "p99_9": 0.3158
    },
    "Frame/Physics/ApplyForces": {
      "min": 0.0206,
      "max": 0.0762,
      "avg": 0.0281,
      "p50": 0.0278,
      "p99": 0.0334,
      "p99_9": 0.0672
    },
    "Frame/Physics/Broadphase": {
      "min": 0.0558,
      "max": 0.1838,
      "avg": 0.1222,
      "p50": 0.1237,
      "p99": 0.1689,
      "p99_9": 0.1813
    },
    "Frame/Physics/Narrowphase": {
      "min": 0.0001,
      "max": 0.0154,
      "avg": 0.0063,
      "p50": 0.006,
      "p99": 0.0109,
      "p99_9": 0.0132
    },
    "Frame/Physics/Terrain": {
      "min": 0.0003,
      "max": 0.0618,
      "avg": 0.0307,
      "p50": 0.0302,
      "p99": 0.0382,
      "p99_9": 0.0553
    },
    "Frame/Physics/Integrate": {
      "min": 0.0003,
      "max": 0.0976,
      "avg": 0.0461,
      "p50": 0.046,
      "p99": 0.0532,
      "p99_9": 0.0795
    },
    "Frame/Text": {
      "min": 0.3912,
      "max": 0.5016,
      "avg": 0.4263,
      "p50": 0.4223,
      "p99": 0.4769,
      "p99_9": 0.4994
    },
    "Frame/PipelineSync": {
      "min": 0.0269,
      "max": 21.1844,
      "avg": 13.5304,
      "p50": 13.548,
      "p99": 20.4147,
      "p99_9": 21.1459
    },
    "Frame/VsyncWait": {
      "min": 0.0913,
      "max": 0.3683,
      "avg": 0.1418,
      "p50": 0.1309,
      "p99": 0.2607,
      "p99_9": 0.323
    }
  },
  "mem_start_mb": 81.32,
  "mem_restart_mb": 84.64,
  "mem_end_mb": 84.64
}